stwno_canteen/__init__.py
stwno_canteen/__main__.py
stwno_canteen/csv_converters.py
stwno_canteen/setup.py
stwno_canteen/stwno_canteen.py
stwno_canteen/stwno_constants.py
stwno_canteen-0.1.dist-info/LICENSE
stwno_canteen-0.1.dist-info/METADATA
stwno_canteen-0.1.dist-info/WHEEL
stwno_canteen-0.1.dist-info/top_level.txt
stwno_canteen-0.1.dist-info/RECORD
