Metadata-Version: 2.1
Name: stwno-canteen
Version: 0.1
Summary: simple API to access the STWNO canteen's menus
Home-page: https://github.com/somsky/stwno_canteen
Author: Stefan Sommer aka somsky
Author-email: stefan.sommer.per@gmail.com
License: MIT
Keywords: stwno
Platform: UNKNOWN
Classifier: Development Status :: 4 - Beta
Classifier: Intended Audience :: Developers
Classifier: License :: OSI Approved :: MIT License
Classifier: Programming Language :: Python :: 3.8
Requires-Python: >=3.8
